volprofile/__init__.py
volprofile/cfg.py
volprofile/main.py
volprofile-1.0.1.dist-info/METADATA
volprofile-1.0.1.dist-info/WHEEL
volprofile-1.0.1.dist-info/RECORD
