Metadata-Version: 2.1
Name: volprofile
Version: 1.0.1
Summary: calculate the volume profile in a flexible manner!
Author: maghrebi
Author-email: sajad.faghfoor@gmail.com
Requires-Python: >=3.6,<4
Classifier: Programming Language :: Python :: 3
Classifier: Programming Language :: Python :: 3.6
Classifier: Programming Language :: Python :: 3.7
Classifier: Programming Language :: Python :: 3.8
Classifier: Programming Language :: Python :: 3.9
Classifier: Programming Language :: Python :: 3.10
Classifier: Programming Language :: Python :: 3.11
Requires-Dist: numpy (>=1.23.4,<2.0.0)
Requires-Dist: pandas (>=1.5.1,<2.0.0)
Requires-Dist: plotly (>=5.11.0,<6.0.0)
